{
	"brandName": "Fendi",
	"color": "black",
	"currency": "EUR",
	"price": 1601,
	"discount": 0.44,
	"typeId"   : null,
	"sizeType": "Italy",
	"quantity": {"40": 1},
	"transport": {
		"duration": {
		"min": 14, 
		"max": 19
		},
		"description": "此商品1个工作日内买手店APP上进行确认，确认后2-5个工作日发货，发货后预计10个工作日左右能到目的地。如遇节假日及海关地检有可能会相应延长（APP会出相应公告）"		
	},
	"pictures": [
		{
			"name": "1.jpg",
			"tags": ["front"]
		},
		{
			"name": "2.jpg",
			"tags": [ "right", "model"]
		},
		{
			"name": "3.jpg",
			"tags": ["front", "model"]
		},
		{
			"name": "4.jpg",
			"tags": ["right", "model","side"]
		},
		{
			"name": "5.jpg",
			"tags": ["back", "model","side"]
		}
	],
	"description": "Fendi（芬迪）蓝色 侧条纹运动裤。套头款式，侧面有对比的拼接。成分：氨纶（弹性纤维）15% 成分：聚酰胺 85% 洗涤说明：手洗",
	"type" : "女士运动裤", 
	"tags": ["female","sport_pants", "pants"]
}